realsense_align_ext.cp310-win32.pyd
realsense_align/__init__.py
realsense_align-0.1.4.dist-info/licenses/LICENSE
realsense_align-0.1.4.dist-info/licenses/NOTICE
realsense_align-0.1.4.dist-info/METADATA
realsense_align-0.1.4.dist-info/WHEEL
realsense_align-0.1.4.dist-info/top_level.txt
realsense_align-0.1.4.dist-info/RECORD
