Metadata-Version: 2.4
Name: realsense-align
Version: 0.1.4
Summary: Python realsense align
Author-email: Louie Lu <git@louie.lu>
License: The Clear BSD License
Project-URL: github, https://github.com/mlouielu/realsense-align
Requires-Python: >=3.8
License-File: LICENSE
License-File: NOTICE
Requires-Dist: pybind11>=2.10.4
Requires-Dist: numpy>=1.22
Dynamic: license-file
